bert/__init__.py
bert/create_pretraining_data.py
bert/extract_features.py
bert/modeling.py
bert/modeling_test.py
bert/optimization.py
bert/optimization_test.py
bert/run_classifier.py
bert/run_classifier_with_tfhub.py
bert/run_pretraining.py
bert/run_squad.py
bert/tokenization.py
bert/tokenization_test.py
bert_tensorflow-1.0.1.dist-info/LICENSE
bert_tensorflow-1.0.1.dist-info/METADATA
bert_tensorflow-1.0.1.dist-info/WHEEL
bert_tensorflow-1.0.1.dist-info/top_level.txt
bert_tensorflow-1.0.1.dist-info/RECORD
