Metadata-Version: 2.1
Name: bert-tensorflow
Version: 1.0.1
Summary: BERT
Home-page: https://github.com/google-research/bert
Author: Google Inc.
Author-email: no-reply@google.com
License: Apache 2.0
Platform: UNKNOWN
Provides-Extra: tensorflow
Provides-Extra: tensorflow_gpu
Provides-Extra: tensorflow-hub
